AnimatedWordCloud/__init__.py
AnimatedWordCloud/__main__.py
AnimatedWordCloud/Animator/AnimationIntegrator.py
AnimatedWordCloud/Animator/Animator.py
AnimatedWordCloud/Animator/ImageCreator.py
AnimatedWordCloud/Animator/__init__.py
AnimatedWordCloud/Animator/AllocationCalculator/AllocationCalculator.py
AnimatedWordCloud/Animator/AllocationCalculator/AnimatetdAllocationCalculator.py
AnimatedWordCloud/Animator/AllocationCalculator/__init__.py
AnimatedWordCloud/Animator/AllocationCalculator/StaticAllocationCalculator/StaticAllocationCalculator.py
AnimatedWordCloud/Animator/AllocationCalculator/StaticAllocationCalculator/__init__.py
AnimatedWordCloud/Animator/AllocationCalculator/StaticAllocationCalculator/StaticAllocationStrategies/RandomAllocation.py
AnimatedWordCloud/Animator/AllocationCalculator/StaticAllocationCalculator/StaticAllocationStrategies/StaticAllocationStrategy.py
AnimatedWordCloud/Animator/AllocationCalculator/StaticAllocationCalculator/StaticAllocationStrategies/__init__.py
AnimatedWordCloud/Animator/AllocationCalculator/StaticAllocationCalculator/StaticAllocationStrategies/MagneticAllocation/MagnetOuterFrontier.py
AnimatedWordCloud/Animator/AllocationCalculator/StaticAllocationCalculator/StaticAllocationStrategies/MagneticAllocation/MagneticAllocation.py
AnimatedWordCloud/Animator/AllocationCalculator/StaticAllocationCalculator/StaticAllocationStrategies/MagneticAllocation/__init__.py
"AnimatedWordCloud/Assets/Fonts/NotoSansMono-VariableFont_wdth,wght.ttf"
AnimatedWordCloud/Utils/Collisions.py
AnimatedWordCloud/Utils/Config.py
AnimatedWordCloud/Utils/Consts.py
AnimatedWordCloud/Utils/FileManager.py
AnimatedWordCloud/Utils/Vector.py
AnimatedWordCloud/Utils/__init__.py
AnimatedWordCloud/Utils/Data/AllocationData.py
AnimatedWordCloud/Utils/Data/Rect.py
AnimatedWordCloud/Utils/Data/TimelapseWordVector.py
AnimatedWordCloud/Utils/Data/Word.py
AnimatedWordCloud/Utils/Data/__init__.py
AnimatedWordCloudTimelapse-1.0.9.dist-info/LICENSE
AnimatedWordCloudTimelapse-1.0.9.dist-info/METADATA
AnimatedWordCloudTimelapse-1.0.9.dist-info/WHEEL
AnimatedWordCloudTimelapse-1.0.9.dist-info/top_level.txt
AnimatedWordCloudTimelapse-1.0.9.dist-info/RECORD
