Metadata-Version: 2.1
Name: AnimatedWordCloudTimelapse
Version: 1.0.9
Summary: Animate a timelapse of word cloud
Home-page: https://github.com/konbraphat51/AnimatedWordCloud/tree/main
Author: konbraphat51, superhotdogcat
Author-email: konbraphat51@gmail.com, siromisochan@gmail.com
License: MIT License
Project-URL: GitHub Repository, https://github.com/konbraphat51/AnimatedWordCloud
Keywords: NLP,World Cloud,Animation,Natural Language Processing,video,Visualization,Data Science
Classifier: Development Status :: 1 - Planning
Classifier: Programming Language :: Python :: 3
Classifier: Intended Audience :: Developers
Classifier: Intended Audience :: Information Technology
Classifier: Intended Audience :: Science/Research
Classifier: License :: OSI Approved :: MIT License
Classifier: Topic :: Multimedia :: Video
Classifier: Topic :: Scientific/Engineering :: Information Analysis
Classifier: Topic :: Text Processing
Requires-Python: >=3.8
License-File: LICENSE
Requires-Dist: Pillow ==10.3.0
Requires-Dist: numpy
Requires-Dist: matplotlib
Requires-Dist: joblib
Requires-Dist: tqdm
